keyboardestop/__init__.py
keyboardestop-0.1.0.dist-info/METADATA
keyboardestop-0.1.0.dist-info/WHEEL
keyboardestop-0.1.0.dist-info/licenses/LICENSE.txt
keyboardestop-0.1.0.dist-info/RECORD
