Metadata-Version: 2.4
Name: keyboardestop
Version: 0.1.0
Summary: Reusable emergency stop helpers for drone SDKs (Ctrl+C and optional key listener).
Project-URL: Homepage, https://example.com/keyboardestop
Project-URL: Repository, https://example.com/keyboardestop
Author: Alexander Deiderich
License: MIT
License-File: LICENSE.txt
Keywords: CoDrone,MAVSDK,drone,emergency,keyboard,signal,stop
Classifier: License :: OSI Approved :: MIT License
Classifier: Operating System :: OS Independent
Classifier: Programming Language :: Python :: 3
Requires-Python: >=3.8
